embeddify/__init__.py
embeddify/embeddify.py
embeddify-0.4.0.dist-info/METADATA
embeddify-0.4.0.dist-info/WHEEL
embeddify-0.4.0.dist-info/top_level.txt
embeddify-0.4.0.dist-info/RECORD
